odoo/addons/pms_partner_identification/README.rst
odoo/addons/pms_partner_identification/__init__.py
odoo/addons/pms_partner_identification/__manifest__.py
odoo/addons/pms_partner_identification/hooks.py
odoo/addons/pms_partner_identification/data/res_partner_id_category.xml
odoo/addons/pms_partner_identification/i18n/es.po
odoo/addons/pms_partner_identification/i18n/it.po
odoo/addons/pms_partner_identification/i18n/pms_partner_identification.pot
odoo/addons/pms_partner_identification/migrations/16.0.1.1.0/pre-migration.py
odoo/addons/pms_partner_identification/models/__init__.py
odoo/addons/pms_partner_identification/models/pms_checkin_partner.py
odoo/addons/pms_partner_identification/models/res_partner.py
odoo/addons/pms_partner_identification/models/res_partner_id_category.py
odoo/addons/pms_partner_identification/models/res_partner_id_number.py
odoo/addons/pms_partner_identification/readme/CONTEXT.rst
odoo/addons/pms_partner_identification/readme/CONTRIBUTORS.rst
odoo/addons/pms_partner_identification/readme/DESCRIPTION.rst
odoo/addons/pms_partner_identification/static/description/icon.png
odoo/addons/pms_partner_identification/static/description/index.html
odoo/addons/pms_partner_identification/tests/__init__.py
odoo/addons/pms_partner_identification/tests/test_pms_checkin_partner.py
odoo/addons/pms_partner_identification/views/pms_checkin_partner.xml
odoo/addons/pms_partner_identification/views/res_partner_id_category.xml
odoo/addons/pms_partner_identification/views/res_partner_id_number.xml
odoo_addon_pms_partner_identification-16.0.2.1.0.3.dist-info/METADATA
odoo_addon_pms_partner_identification-16.0.2.1.0.3.dist-info/WHEEL
odoo_addon_pms_partner_identification-16.0.2.1.0.3.dist-info/top_level.txt
odoo_addon_pms_partner_identification-16.0.2.1.0.3.dist-info/RECORD
