Metadata-Version: 2.1
Name: odoo-addon-pms_partner_identification
Version: 16.0.2.1.0.3
Summary: Add identification models in pms
Home-page: https://github.com/OCA/pms
Author: Commit [Sun], Odoo Community Association (OCA)
Author-email: support@odoo-community.org
License: AGPL-3
Classifier: Programming Language :: Python
Classifier: Framework :: Odoo
Classifier: Framework :: Odoo :: 16.0
Classifier: License :: OSI Approved :: GNU Affero General Public License v3
Classifier: Development Status :: 4 - Beta
Requires-Python: >=3.10
Requires-Dist: odoo-addon-partner-identification<16.1dev,>=16.0dev
Requires-Dist: odoo-addon-pms<16.1dev,>=16.0dev
Requires-Dist: odoo<16.1dev,>=16.0a
Requires-Dist: openupgradelib
